{
"Ocassions" : [ {"item": "Ocassions","id": 1,  "url" : "#HREF"}, 
                {"item": "Working from Home","id": 2, "url" : "#HREF"}, 
                {"item":"Snack Time","id": 3, "url" : "#HREF"},
                {"item":"Breakfast","id": 4, "url" : "#HREF"},
                {"item":"Vegan Life", "id": 5,"url" : "#HREF"},
                {"item":"Baking","id": 6, "url" : "#HREF"},
                {"item":"Gifts & Bundles","id": 7, "url" : "#HREF"},
                {"item":"Easy Cooking", "id": 8,"url" : "#HREF"},
                {"item":"All products","id": 9, "url" : "#HREF"}
            ],
"All Categories": [ 
            {"item" : "Baking","id" : 1, "url" : "#HREF"},
            {"item" : "Breakfast", "id" : 2, "url" : "#HREF"},
            {"item" :"Condiments", "id" : 3, "url" : "#HREF"},
            {"item" :"Drinks", "id" : 4, "url" : "#HREF"},
            {"item" :"Heat things up", "id" : 5, "url" : "#HREF"},
            {"item" :"Meal Solutions", "id" : 6, "url" : "#HREF"},
            {"item" :"Pantry staples", "id" : 7, "url" : "#HREF"},
            {"item" :"Simmer Sauces", "id" : 8, "url" : "#HREF"},
            {"item" :"Snacks & Treats", "id" : 9, "url" : "#HREF"},
            {"item" :"Spice Up Your Cooking", "id" : 10, "url" : "#HREF"},
            {"item" :"Sweet Tooth", "id" : 11, "url" : "#HREF"},
            {"item" :"Wines & Cheese", "id" : 12, "url" : "#HREF"},
            {"item" :"All Products", "id" : 13, "url" : "#HREF"}
        ],
"Gifts & Bundles": [ 
            {"item" : "Sweet Tooth Special","id" : 1, "url" : "#HREF"},
            {"item" : "Discover Local", "id" : 2, "url" : "#HREF"},
            {"item" :"Baking Box", "id" : 3, "url" : "#HREF"},
            {"item" :"Spicy Heat Lover's Box", "id" : 4, "url" : "#HREF"},
            {"item" :"Snacking Sensations", "id" : 5, "url" : "#HREF"}
        ],
"Our Brands" : [
        ],
"About Us": [
    
]
}

